tripletlib/__init__.py
tripletlib/evaluation_utils.py
tripletlib/triplet_utils.py
tripletlib-0.1.1.dist-info/licenses/LICENSE
tripletlib-0.1.1.dist-info/METADATA
tripletlib-0.1.1.dist-info/WHEEL
tripletlib-0.1.1.dist-info/top_level.txt
tripletlib-0.1.1.dist-info/RECORD
