Metadata-Version: 2.4
Name: tripletlib
Version: 0.1.1
Summary: A lightweight library for training and evaluating embedding models with triplet loss
Author: Ted Kane
License: MIT
Requires-Python: >=3.8
License-File: LICENSE
Requires-Dist: torch
Requires-Dist: numpy
Requires-Dist: scikit-learn
Requires-Dist: scipy
Provides-Extra: examples
Requires-Dist: matplotlib; extra == "examples"
Requires-Dist: pandas; extra == "examples"
Dynamic: license-file
